honeybee_energy/__init__.py
honeybee_energy/__main__.py
honeybee_energy/_extend_honeybee.py
honeybee_energy/altnumber.py
honeybee_energy/boundarycondition.py
honeybee_energy/config.json
honeybee_energy/config.py
honeybee_energy/constructionset.py
honeybee_energy/dictutil.py
honeybee_energy/internalmass.py
honeybee_energy/measure.py
honeybee_energy/programtype.py
honeybee_energy/reader.py
honeybee_energy/run.py
honeybee_energy/shw.py
honeybee_energy/writer.py
honeybee_energy/baseline/__init__.py
honeybee_energy/baseline/create.py
honeybee_energy/baseline/pci.py
honeybee_energy/baseline/result.py
honeybee_energy/baseline/data/__init__.py
honeybee_energy/baseline/data/constructions.csv
honeybee_energy/baseline/data/fen_ratios.csv
honeybee_energy/baseline/data/lpd_building.csv
honeybee_energy/baseline/data/pci_2016.csv
honeybee_energy/baseline/data/pci_2019.csv
honeybee_energy/baseline/data/pci_2022.csv
honeybee_energy/baseline/data/shw.csv
honeybee_energy/cli/__init__.py
honeybee_energy/cli/baseline.py
honeybee_energy/cli/edit.py
honeybee_energy/cli/lib.py
honeybee_energy/cli/result.py
honeybee_energy/cli/setconfig.py
honeybee_energy/cli/settings.py
honeybee_energy/cli/simulate.py
honeybee_energy/cli/translate.py
honeybee_energy/cli/validate.py
honeybee_energy/construction/__init__.py
honeybee_energy/construction/_base.py
honeybee_energy/construction/air.py
honeybee_energy/construction/dictutil.py
honeybee_energy/construction/dynamic.py
honeybee_energy/construction/opaque.py
honeybee_energy/construction/shade.py
honeybee_energy/construction/window.py
honeybee_energy/construction/windowshade.py
honeybee_energy/generator/__init__.py
honeybee_energy/generator/loadcenter.py
honeybee_energy/generator/pv.py
honeybee_energy/hvac/__init__.py
honeybee_energy/hvac/_base.py
honeybee_energy/hvac/_template.py
honeybee_energy/hvac/detailed.py
honeybee_energy/hvac/idealair.py
honeybee_energy/hvac/allair/__init__.py
honeybee_energy/hvac/allair/_base.py
honeybee_energy-1.116.111.dist-info/licenses/LICENSE
honeybee_energy-1.116.111.dist-info/METADATA
honeybee_energy-1.116.111.dist-info/WHEEL
honeybee_energy-1.116.111.dist-info/entry_points.txt
honeybee_energy-1.116.111.dist-info/top_level.txt
honeybee_energy-1.116.111.dist-info/RECORD
